README.rst
flask_bouncer.py
setup.cfg
setup.py
flask_bouncer.egg-info/PKG-INFO
flask_bouncer.egg-info/SOURCES.txt
flask_bouncer.egg-info/dependency_links.txt
flask_bouncer.egg-info/not-zip-safe
flask_bouncer.egg-info/requires.txt
flask_bouncer.egg-info/top_level.txt