Metadata-Version: 1.1
Name: flask-bouncer
Version: 0.1.13
Summary: Flask Simple Declarative Authentication based on Ryan Bates excellent cancan library
Home-page: http://github.com/jtushman/flask-bouncer
Author: Jonathan Tushman
Author-email: jonathan@zefr.com
License: MIT
Platform: any
Classifier: Environment :: Web Environment
Classifier: Intended Audience :: Developers
Classifier: License :: OSI Approved :: BSD License
Classifier: Operating System :: OS Independent
Classifier: Programming Language :: Python
Classifier: Topic :: Internet :: WWW/HTTP :: Dynamic Content
Classifier: Topic :: Software Development :: Libraries :: Python Modules
